[1,["4fa3UGEgdPD7abvZiKMsMb@6c48a"],["_textureSource"],["cc.SpriteFrame","cc.SpriteAtlas"],0,[[[{"name":"shopkeeper_brown","spriteFrames":["shopkeeper_brown__face_back","c91gPgqhVID43NsLPN9HZa@a6e8e","shopkeeper_brown__face_front","c91gPgqhVID43NsLPN9HZa@521b7","shopkeeper_brown__face_left","c91gPgqhVID43NsLPN9HZa@64468","shopkeeper_brown__face_right","c91gPgqhVID43NsLPN9HZa@0513b","shopkeeper_brown__walk_back_000","c91gPgqhVID43NsLPN9HZa@3f053","shopkeeper_brown__walk_back_001","c91gPgqhVID43NsLPN9HZa@0fef1","shopkeeper_brown__walk_back_002","c91gPgqhVID43NsLPN9HZa@8230e","shopkeeper_brown__walk_back_003","c91gPgqhVID43NsLPN9HZa@ffd0a","shopkeeper_brown__walk_front_000","c91gPgqhVID43NsLPN9HZa@79874","shopkeeper_brown__walk_front_001","c91gPgqhVID43NsLPN9HZa@8e478","shopkeeper_brown__walk_front_002","c91gPgqhVID43NsLPN9HZa@594e6","shopkeeper_brown__walk_front_003","c91gPgqhVID43NsLPN9HZa@5d505","shopkeeper_brown__walk_left_000","c91gPgqhVID43NsLPN9HZa@a5b3e","shopkeeper_brown__walk_left_001","c91gPgqhVID43NsLPN9HZa@6bc73","shopkeeper_brown__walk_left_002","c91gPgqhVID43NsLPN9HZa@ca17c","shopkeeper_brown__walk_left_003","c91gPgqhVID43NsLPN9HZa@13127","shopkeeper_brown__walk_right_000","c91gPgqhVID43NsLPN9HZa@75f5f","shopkeeper_brown__walk_right_001","c91gPgqhVID43NsLPN9HZa@4549a","shopkeeper_brown__walk_right_002","c91gPgqhVID43NsLPN9HZa@ac85f","shopkeeper_brown__walk_right_003","c91gPgqhVID43NsLPN9HZa@afdc8"]}],[1],0,[],[],[]],[[{"name":"shopkeeper_brown__face_right","rect":{"x":48,"y":0,"width":16,"height":32},"offset":{"x":0,"y":0},"originalSize":{"width":16,"height":32},"rotated":false,"capInsets":[0,0,0,0],"vertices":{"rawPosition":[],"indexes":[],"uv":[],"nuv":[],"minPos":{"x":0,"y":0,"z":0},"maxPos":{"x":0,"y":0,"z":0}},"packable":true,"pixelsToUnit":100,"pivot":{"x":0.5,"y":0.5},"meshType":0}],[0],0,[0],[0],[0]],[[{"name":"shopkeeper_brown__walk_back_001","rect":{"x":80,"y":0,"width":16,"height":32},"offset":{"x":0,"y":0},"originalSize":{"width":16,"height":32},"rotated":false,"capInsets":[0,0,0,0],"vertices":{"rawPosition":[],"indexes":[],"uv":[],"nuv":[],"minPos":{"x":0,"y":0,"z":0},"maxPos":{"x":0,"y":0,"z":0}},"packable":true,"pixelsToUnit":100,"pivot":{"x":0.5,"y":0.5},"meshType":0}],[0],0,[0],[0],[0]],[[{"name":"shopkeeper_brown__walk_left_003","rect":{"x":240,"y":0,"width":16,"height":32},"offset":{"x":0,"y":0},"originalSize":{"width":16,"height":32},"rotated":false,"capInsets":[0,0,0,0],"vertices":{"rawPosition":[],"indexes":[],"uv":[],"nuv":[],"minPos":{"x":0,"y":0,"z":0},"maxPos":{"x":0,"y":0,"z":0}},"packable":true,"pixelsToUnit":100,"pivot":{"x":0.5,"y":0.5},"meshType":0}],[0],0,[0],[0],[0]],[[{"name":"shopkeeper_brown__walk_back_000","rect":{"x":64,"y":0,"width":16,"height":32},"offset":{"x":0,"y":0},"originalSize":{"width":16,"height":32},"rotated":false,"capInsets":[0,0,0,0],"vertices":{"rawPosition":[],"indexes":[],"uv":[],"nuv":[],"minPos":{"x":0,"y":0,"z":0},"maxPos":{"x":0,"y":0,"z":0}},"packable":true,"pixelsToUnit":100,"pivot":{"x":0.5,"y":0.5},"meshType":0}],[0],0,[0],[0],[0]],[[{"name":"shopkeeper_brown__walk_right_001","rect":{"x":272,"y":0,"width":16,"height":32},"offset":{"x":0,"y":0},"originalSize":{"width":16,"height":32},"rotated":false,"capInsets":[0,0,0,0],"vertices":{"rawPosition":[],"indexes":[],"uv":[],"nuv":[],"minPos":{"x":0,"y":0,"z":0},"maxPos":{"x":0,"y":0,"z":0}},"packable":true,"pixelsToUnit":100,"pivot":{"x":0.5,"y":0.5},"meshType":0}],[0],0,[0],[0],[0]],[[{"name":"shopkeeper_brown__face_front","rect":{"x":16,"y":0,"width":16,"height":32},"offset":{"x":0,"y":0},"originalSize":{"width":16,"height":32},"rotated":false,"capInsets":[0,0,0,0],"vertices":{"rawPosition":[],"indexes":[],"uv":[],"nuv":[],"minPos":{"x":0,"y":0,"z":0},"maxPos":{"x":0,"y":0,"z":0}},"packable":true,"pixelsToUnit":100,"pivot":{"x":0.5,"y":0.5},"meshType":0}],[0],0,[0],[0],[0]],[[{"name":"shopkeeper_brown__walk_front_002","rect":{"x":160,"y":0,"width":16,"height":32},"offset":{"x":0,"y":0},"originalSize":{"width":16,"height":32},"rotated":false,"capInsets":[0,0,0,0],"vertices":{"rawPosition":[],"indexes":[],"uv":[],"nuv":[],"minPos":{"x":0,"y":0,"z":0},"maxPos":{"x":0,"y":0,"z":0}},"packable":true,"pixelsToUnit":100,"pivot":{"x":0.5,"y":0.5},"meshType":0}],[0],0,[0],[0],[0]],[[{"name":"shopkeeper_brown__walk_front_003","rect":{"x":176,"y":0,"width":16,"height":32},"offset":{"x":0,"y":0},"originalSize":{"width":16,"height":32},"rotated":false,"capInsets":[0,0,0,0],"vertices":{"rawPosition":[],"indexes":[],"uv":[],"nuv":[],"minPos":{"x":0,"y":0,"z":0},"maxPos":{"x":0,"y":0,"z":0}},"packable":true,"pixelsToUnit":100,"pivot":{"x":0.5,"y":0.5},"meshType":0}],[0],0,[0],[0],[0]],[[{"name":"shopkeeper_brown__face_left","rect":{"x":32,"y":0,"width":16,"height":32},"offset":{"x":0,"y":0},"originalSize":{"width":16,"height":32},"rotated":false,"capInsets":[0,0,0,0],"vertices":{"rawPosition":[],"indexes":[],"uv":[],"nuv":[],"minPos":{"x":0,"y":0,"z":0},"maxPos":{"x":0,"y":0,"z":0}},"packable":true,"pixelsToUnit":100,"pivot":{"x":0.5,"y":0.5},"meshType":0}],[0],0,[0],[0],[0]],[[{"name":"shopkeeper_brown__walk_left_001","rect":{"x":208,"y":0,"width":16,"height":32},"offset":{"x":0,"y":0},"originalSize":{"width":16,"height":32},"rotated":false,"capInsets":[0,0,0,0],"vertices":{"rawPosition":[],"indexes":[],"uv":[],"nuv":[],"minPos":{"x":0,"y":0,"z":0},"maxPos":{"x":0,"y":0,"z":0}},"packable":true,"pixelsToUnit":100,"pivot":{"x":0.5,"y":0.5},"meshType":0}],[0],0,[0],[0],[0]],[[{"name":"shopkeeper_brown__walk_right_000","rect":{"x":256,"y":0,"width":16,"height":32},"offset":{"x":0,"y":0},"originalSize":{"width":16,"height":32},"rotated":false,"capInsets":[0,0,0,0],"vertices":{"rawPosition":[],"indexes":[],"uv":[],"nuv":[],"minPos":{"x":0,"y":0,"z":0},"maxPos":{"x":0,"y":0,"z":0}},"packable":true,"pixelsToUnit":100,"pivot":{"x":0.5,"y":0.5},"meshType":0}],[0],0,[0],[0],[0]],[[{"name":"shopkeeper_brown__walk_front_000","rect":{"x":128,"y":0,"width":16,"height":32},"offset":{"x":0,"y":0},"originalSize":{"width":16,"height":32},"rotated":false,"capInsets":[0,0,0,0],"vertices":{"rawPosition":[],"indexes":[],"uv":[],"nuv":[],"minPos":{"x":0,"y":0,"z":0},"maxPos":{"x":0,"y":0,"z":0}},"packable":true,"pixelsToUnit":100,"pivot":{"x":0.5,"y":0.5},"meshType":0}],[0],0,[0],[0],[0]],[[{"name":"shopkeeper_brown__walk_back_002","rect":{"x":96,"y":0,"width":16,"height":32},"offset":{"x":0,"y":0},"originalSize":{"width":16,"height":32},"rotated":false,"capInsets":[0,0,0,0],"vertices":{"rawPosition":[],"indexes":[],"uv":[],"nuv":[],"minPos":{"x":0,"y":0,"z":0},"maxPos":{"x":0,"y":0,"z":0}},"packable":true,"pixelsToUnit":100,"pivot":{"x":0.5,"y":0.5},"meshType":0}],[0],0,[0],[0],[0]],[[{"name":"shopkeeper_brown__walk_front_001","rect":{"x":144,"y":0,"width":16,"height":32},"offset":{"x":0,"y":0},"originalSize":{"width":16,"height":32},"rotated":false,"capInsets":[0,0,0,0],"vertices":{"rawPosition":[],"indexes":[],"uv":[],"nuv":[],"minPos":{"x":0,"y":0,"z":0},"maxPos":{"x":0,"y":0,"z":0}},"packable":true,"pixelsToUnit":100,"pivot":{"x":0.5,"y":0.5},"meshType":0}],[0],0,[0],[0],[0]],[[{"name":"shopkeeper_brown__walk_left_000","rect":{"x":192,"y":0,"width":16,"height":32},"offset":{"x":0,"y":0},"originalSize":{"width":16,"height":32},"rotated":false,"capInsets":[0,0,0,0],"vertices":{"rawPosition":[],"indexes":[],"uv":[],"nuv":[],"minPos":{"x":0,"y":0,"z":0},"maxPos":{"x":0,"y":0,"z":0}},"packable":true,"pixelsToUnit":100,"pivot":{"x":0.5,"y":0.5},"meshType":0}],[0],0,[0],[0],[0]],[[{"name":"shopkeeper_brown__face_back","rect":{"x":0,"y":0,"width":16,"height":32},"offset":{"x":0,"y":0},"originalSize":{"width":16,"height":32},"rotated":false,"capInsets":[0,0,0,0],"vertices":{"rawPosition":[],"indexes":[],"uv":[],"nuv":[],"minPos":{"x":0,"y":0,"z":0},"maxPos":{"x":0,"y":0,"z":0}},"packable":true,"pixelsToUnit":100,"pivot":{"x":0.5,"y":0.5},"meshType":0}],[0],0,[0],[0],[0]],[[{"name":"shopkeeper_brown__walk_right_002","rect":{"x":288,"y":0,"width":16,"height":32},"offset":{"x":0,"y":0},"originalSize":{"width":16,"height":32},"rotated":false,"capInsets":[0,0,0,0],"vertices":{"rawPosition":[],"indexes":[],"uv":[],"nuv":[],"minPos":{"x":0,"y":0,"z":0},"maxPos":{"x":0,"y":0,"z":0}},"packable":true,"pixelsToUnit":100,"pivot":{"x":0.5,"y":0.5},"meshType":0}],[0],0,[0],[0],[0]],[[{"name":"shopkeeper_brown__walk_right_003","rect":{"x":304,"y":0,"width":16,"height":32},"offset":{"x":0,"y":0},"originalSize":{"width":16,"height":32},"rotated":false,"capInsets":[0,0,0,0],"vertices":{"rawPosition":[],"indexes":[],"uv":[],"nuv":[],"minPos":{"x":0,"y":0,"z":0},"maxPos":{"x":0,"y":0,"z":0}},"packable":true,"pixelsToUnit":100,"pivot":{"x":0.5,"y":0.5},"meshType":0}],[0],0,[0],[0],[0]],[[{"name":"shopkeeper_brown__walk_left_002","rect":{"x":224,"y":0,"width":16,"height":32},"offset":{"x":0,"y":0},"originalSize":{"width":16,"height":32},"rotated":false,"capInsets":[0,0,0,0],"vertices":{"rawPosition":[],"indexes":[],"uv":[],"nuv":[],"minPos":{"x":0,"y":0,"z":0},"maxPos":{"x":0,"y":0,"z":0}},"packable":true,"pixelsToUnit":100,"pivot":{"x":0.5,"y":0.5},"meshType":0}],[0],0,[0],[0],[0]],[[{"name":"shopkeeper_brown__walk_back_003","rect":{"x":112,"y":0,"width":16,"height":32},"offset":{"x":0,"y":0},"originalSize":{"width":16,"height":32},"rotated":false,"capInsets":[0,0,0,0],"vertices":{"rawPosition":[],"indexes":[],"uv":[],"nuv":[],"minPos":{"x":0,"y":0,"z":0},"maxPos":{"x":0,"y":0,"z":0}},"packable":true,"pixelsToUnit":100,"pivot":{"x":0.5,"y":0.5},"meshType":0}],[0],0,[0],[0],[0]]]]
