[1,["ad1R1U4NBHxrLs+LM77lfc@6c48a"],["_textureSource"],["cc.SpriteFrame","cc.SpriteAtlas"],0,[[[{"name":"maniac_01","spriteFrames":["maniac_01__face_back","02THe2HOlBVZ0TqVTNJLui@fa255","maniac_01__face_front","02THe2HOlBVZ0TqVTNJLui@925d9","maniac_01__face_left","02THe2HOlBVZ0TqVTNJLui@1ac25","maniac_01__face_right","02THe2HOlBVZ0TqVTNJLui@225c5","maniac_01__walk_back_000","02THe2HOlBVZ0TqVTNJLui@24734","maniac_01__walk_back_001","02THe2HOlBVZ0TqVTNJLui@791a4","maniac_01__walk_back_002","02THe2HOlBVZ0TqVTNJLui@1edbd","maniac_01__walk_back_003","02THe2HOlBVZ0TqVTNJLui@ad2c1","maniac_01__walk_front_000","02THe2HOlBVZ0TqVTNJLui@ec98c","maniac_01__walk_front_001","02THe2HOlBVZ0TqVTNJLui@c3668","maniac_01__walk_front_002","02THe2HOlBVZ0TqVTNJLui@b328e","maniac_01__walk_front_003","02THe2HOlBVZ0TqVTNJLui@d24c0","maniac_01__walk_left_000","02THe2HOlBVZ0TqVTNJLui@17833","maniac_01__walk_left_001","02THe2HOlBVZ0TqVTNJLui@82097","maniac_01__walk_left_002","02THe2HOlBVZ0TqVTNJLui@cbe77","maniac_01__walk_left_003","02THe2HOlBVZ0TqVTNJLui@50fcb","maniac_01__walk_right_000","02THe2HOlBVZ0TqVTNJLui@bbc6d","maniac_01__walk_right_001","02THe2HOlBVZ0TqVTNJLui@ac55f","maniac_01__walk_right_002","02THe2HOlBVZ0TqVTNJLui@89e8b","maniac_01__walk_right_003","02THe2HOlBVZ0TqVTNJLui@33e25"]}],[1],0,[],[],[]],[[{"name":"maniac_01__walk_left_000","rect":{"x":32,"y":0,"width":16,"height":32},"offset":{"x":0,"y":0},"originalSize":{"width":16,"height":32},"rotated":false,"capInsets":[0,0,0,0],"vertices":{"rawPosition":[],"indexes":[],"uv":[],"nuv":[],"minPos":{"x":0,"y":0,"z":0},"maxPos":{"x":0,"y":0,"z":0}},"packable":true,"pixelsToUnit":100,"pivot":{"x":0.5,"y":0.5},"meshType":0}],[0],0,[0],[0],[0]],[[{"name":"maniac_01__face_left","rect":{"x":32,"y":0,"width":16,"height":32},"offset":{"x":0,"y":0},"originalSize":{"width":16,"height":32},"rotated":false,"capInsets":[0,0,0,0],"vertices":{"rawPosition":[],"indexes":[],"uv":[],"nuv":[],"minPos":{"x":0,"y":0,"z":0},"maxPos":{"x":0,"y":0,"z":0}},"packable":true,"pixelsToUnit":100,"pivot":{"x":0.5,"y":0.5},"meshType":0}],[0],0,[0],[0],[0]],[[{"name":"maniac_01__walk_back_002","rect":{"x":0,"y":0,"width":16,"height":32},"offset":{"x":0,"y":0},"originalSize":{"width":16,"height":32},"rotated":false,"capInsets":[0,0,0,0],"vertices":{"rawPosition":[],"indexes":[],"uv":[],"nuv":[],"minPos":{"x":0,"y":0,"z":0},"maxPos":{"x":0,"y":0,"z":0}},"packable":true,"pixelsToUnit":100,"pivot":{"x":0.5,"y":0.5},"meshType":0}],[0],0,[0],[0],[0]],[[{"name":"maniac_01__face_right","rect":{"x":48,"y":0,"width":16,"height":32},"offset":{"x":0,"y":0},"originalSize":{"width":16,"height":32},"rotated":false,"capInsets":[0,0,0,0],"vertices":{"rawPosition":[],"indexes":[],"uv":[],"nuv":[],"minPos":{"x":0,"y":0,"z":0},"maxPos":{"x":0,"y":0,"z":0}},"packable":true,"pixelsToUnit":100,"pivot":{"x":0.5,"y":0.5},"meshType":0}],[0],0,[0],[0],[0]],[[{"name":"maniac_01__walk_back_000","rect":{"x":0,"y":0,"width":16,"height":32},"offset":{"x":0,"y":0},"originalSize":{"width":16,"height":32},"rotated":false,"capInsets":[0,0,0,0],"vertices":{"rawPosition":[],"indexes":[],"uv":[],"nuv":[],"minPos":{"x":0,"y":0,"z":0},"maxPos":{"x":0,"y":0,"z":0}},"packable":true,"pixelsToUnit":100,"pivot":{"x":0.5,"y":0.5},"meshType":0}],[0],0,[0],[0],[0]],[[{"name":"maniac_01__walk_right_003","rect":{"x":48,"y":0,"width":16,"height":32},"offset":{"x":0,"y":0},"originalSize":{"width":16,"height":32},"rotated":false,"capInsets":[0,0,0,0],"vertices":{"rawPosition":[],"indexes":[],"uv":[],"nuv":[],"minPos":{"x":0,"y":0,"z":0},"maxPos":{"x":0,"y":0,"z":0}},"packable":true,"pixelsToUnit":100,"pivot":{"x":0.5,"y":0.5},"meshType":0}],[0],0,[0],[0],[0]],[[{"name":"maniac_01__walk_left_003","rect":{"x":32,"y":0,"width":16,"height":32},"offset":{"x":0,"y":0},"originalSize":{"width":16,"height":32},"rotated":false,"capInsets":[0,0,0,0],"vertices":{"rawPosition":[],"indexes":[],"uv":[],"nuv":[],"minPos":{"x":0,"y":0,"z":0},"maxPos":{"x":0,"y":0,"z":0}},"packable":true,"pixelsToUnit":100,"pivot":{"x":0.5,"y":0.5},"meshType":0}],[0],0,[0],[0],[0]],[[{"name":"maniac_01__walk_back_001","rect":{"x":0,"y":0,"width":16,"height":32},"offset":{"x":0,"y":0},"originalSize":{"width":16,"height":32},"rotated":false,"capInsets":[0,0,0,0],"vertices":{"rawPosition":[],"indexes":[],"uv":[],"nuv":[],"minPos":{"x":0,"y":0,"z":0},"maxPos":{"x":0,"y":0,"z":0}},"packable":true,"pixelsToUnit":100,"pivot":{"x":0.5,"y":0.5},"meshType":0}],[0],0,[0],[0],[0]],[[{"name":"maniac_01__walk_left_001","rect":{"x":32,"y":0,"width":16,"height":32},"offset":{"x":0,"y":0},"originalSize":{"width":16,"height":32},"rotated":false,"capInsets":[0,0,0,0],"vertices":{"rawPosition":[],"indexes":[],"uv":[],"nuv":[],"minPos":{"x":0,"y":0,"z":0},"maxPos":{"x":0,"y":0,"z":0}},"packable":true,"pixelsToUnit":100,"pivot":{"x":0.5,"y":0.5},"meshType":0}],[0],0,[0],[0],[0]],[[{"name":"maniac_01__walk_right_002","rect":{"x":48,"y":0,"width":16,"height":32},"offset":{"x":0,"y":0},"originalSize":{"width":16,"height":32},"rotated":false,"capInsets":[0,0,0,0],"vertices":{"rawPosition":[],"indexes":[],"uv":[],"nuv":[],"minPos":{"x":0,"y":0,"z":0},"maxPos":{"x":0,"y":0,"z":0}},"packable":true,"pixelsToUnit":100,"pivot":{"x":0.5,"y":0.5},"meshType":0}],[0],0,[0],[0],[0]],[[{"name":"maniac_01__face_front","rect":{"x":16,"y":0,"width":16,"height":32},"offset":{"x":0,"y":0},"originalSize":{"width":16,"height":32},"rotated":false,"capInsets":[0,0,0,0],"vertices":{"rawPosition":[],"indexes":[],"uv":[],"nuv":[],"minPos":{"x":0,"y":0,"z":0},"maxPos":{"x":0,"y":0,"z":0}},"packable":true,"pixelsToUnit":100,"pivot":{"x":0.5,"y":0.5},"meshType":0}],[0],0,[0],[0],[0]],[[{"name":"maniac_01__walk_right_001","rect":{"x":48,"y":0,"width":16,"height":32},"offset":{"x":0,"y":0},"originalSize":{"width":16,"height":32},"rotated":false,"capInsets":[0,0,0,0],"vertices":{"rawPosition":[],"indexes":[],"uv":[],"nuv":[],"minPos":{"x":0,"y":0,"z":0},"maxPos":{"x":0,"y":0,"z":0}},"packable":true,"pixelsToUnit":100,"pivot":{"x":0.5,"y":0.5},"meshType":0}],[0],0,[0],[0],[0]],[[{"name":"maniac_01__walk_back_003","rect":{"x":0,"y":0,"width":16,"height":32},"offset":{"x":0,"y":0},"originalSize":{"width":16,"height":32},"rotated":false,"capInsets":[0,0,0,0],"vertices":{"rawPosition":[],"indexes":[],"uv":[],"nuv":[],"minPos":{"x":0,"y":0,"z":0},"maxPos":{"x":0,"y":0,"z":0}},"packable":true,"pixelsToUnit":100,"pivot":{"x":0.5,"y":0.5},"meshType":0}],[0],0,[0],[0],[0]],[[{"name":"maniac_01__walk_front_002","rect":{"x":16,"y":0,"width":16,"height":32},"offset":{"x":0,"y":0},"originalSize":{"width":16,"height":32},"rotated":false,"capInsets":[0,0,0,0],"vertices":{"rawPosition":[],"indexes":[],"uv":[],"nuv":[],"minPos":{"x":0,"y":0,"z":0},"maxPos":{"x":0,"y":0,"z":0}},"packable":true,"pixelsToUnit":100,"pivot":{"x":0.5,"y":0.5},"meshType":0}],[0],0,[0],[0],[0]],[[{"name":"maniac_01__walk_right_000","rect":{"x":48,"y":0,"width":16,"height":32},"offset":{"x":0,"y":0},"originalSize":{"width":16,"height":32},"rotated":false,"capInsets":[0,0,0,0],"vertices":{"rawPosition":[],"indexes":[],"uv":[],"nuv":[],"minPos":{"x":0,"y":0,"z":0},"maxPos":{"x":0,"y":0,"z":0}},"packable":true,"pixelsToUnit":100,"pivot":{"x":0.5,"y":0.5},"meshType":0}],[0],0,[0],[0],[0]],[[{"name":"maniac_01__walk_front_001","rect":{"x":16,"y":0,"width":16,"height":32},"offset":{"x":0,"y":0},"originalSize":{"width":16,"height":32},"rotated":false,"capInsets":[0,0,0,0],"vertices":{"rawPosition":[],"indexes":[],"uv":[],"nuv":[],"minPos":{"x":0,"y":0,"z":0},"maxPos":{"x":0,"y":0,"z":0}},"packable":true,"pixelsToUnit":100,"pivot":{"x":0.5,"y":0.5},"meshType":0}],[0],0,[0],[0],[0]],[[{"name":"maniac_01__walk_left_002","rect":{"x":32,"y":0,"width":16,"height":32},"offset":{"x":0,"y":0},"originalSize":{"width":16,"height":32},"rotated":false,"capInsets":[0,0,0,0],"vertices":{"rawPosition":[],"indexes":[],"uv":[],"nuv":[],"minPos":{"x":0,"y":0,"z":0},"maxPos":{"x":0,"y":0,"z":0}},"packable":true,"pixelsToUnit":100,"pivot":{"x":0.5,"y":0.5},"meshType":0}],[0],0,[0],[0],[0]],[[{"name":"maniac_01__walk_front_003","rect":{"x":16,"y":0,"width":16,"height":32},"offset":{"x":0,"y":0},"originalSize":{"width":16,"height":32},"rotated":false,"capInsets":[0,0,0,0],"vertices":{"rawPosition":[],"indexes":[],"uv":[],"nuv":[],"minPos":{"x":0,"y":0,"z":0},"maxPos":{"x":0,"y":0,"z":0}},"packable":true,"pixelsToUnit":100,"pivot":{"x":0.5,"y":0.5},"meshType":0}],[0],0,[0],[0],[0]],[[{"name":"maniac_01__walk_front_000","rect":{"x":16,"y":0,"width":16,"height":32},"offset":{"x":0,"y":0},"originalSize":{"width":16,"height":32},"rotated":false,"capInsets":[0,0,0,0],"vertices":{"rawPosition":[],"indexes":[],"uv":[],"nuv":[],"minPos":{"x":0,"y":0,"z":0},"maxPos":{"x":0,"y":0,"z":0}},"packable":true,"pixelsToUnit":100,"pivot":{"x":0.5,"y":0.5},"meshType":0}],[0],0,[0],[0],[0]],[[{"name":"maniac_01__face_back","rect":{"x":0,"y":0,"width":16,"height":32},"offset":{"x":0,"y":0},"originalSize":{"width":16,"height":32},"rotated":false,"capInsets":[0,0,0,0],"vertices":{"rawPosition":[],"indexes":[],"uv":[],"nuv":[],"minPos":{"x":0,"y":0,"z":0},"maxPos":{"x":0,"y":0,"z":0}},"packable":true,"pixelsToUnit":100,"pivot":{"x":0.5,"y":0.5},"meshType":0}],[0],0,[0],[0],[0]]]]
