[1,["c7pA2XYh5AhrTNE0oH3RNb@6c48a"],["_textureSource"],["cc.SpriteFrame","cc.SpriteAtlas"],0,[[[{"name":"beachcomber_gray","spriteFrames":["beachcomber_gray__face_back","d1i4KASghMdph5ECIc+7P9@4b3f8","beachcomber_gray__face_front","d1i4KASghMdph5ECIc+7P9@7ec44","beachcomber_gray__face_left","d1i4KASghMdph5ECIc+7P9@255a3","beachcomber_gray__face_right","d1i4KASghMdph5ECIc+7P9@aa1b7","beachcomber_gray__walk_back_000","d1i4KASghMdph5ECIc+7P9@11eed","beachcomber_gray__walk_back_001","d1i4KASghMdph5ECIc+7P9@40d81","beachcomber_gray__walk_back_002","d1i4KASghMdph5ECIc+7P9@8c26a","beachcomber_gray__walk_back_003","d1i4KASghMdph5ECIc+7P9@c7a8c","beachcomber_gray__walk_front_000","d1i4KASghMdph5ECIc+7P9@473a9","beachcomber_gray__walk_front_001","d1i4KASghMdph5ECIc+7P9@2b053","beachcomber_gray__walk_front_002","d1i4KASghMdph5ECIc+7P9@51bd6","beachcomber_gray__walk_front_003","d1i4KASghMdph5ECIc+7P9@919af","beachcomber_gray__walk_left_000","d1i4KASghMdph5ECIc+7P9@9eca6","beachcomber_gray__walk_left_001","d1i4KASghMdph5ECIc+7P9@b4a80","beachcomber_gray__walk_left_002","d1i4KASghMdph5ECIc+7P9@173e4","beachcomber_gray__walk_left_003","d1i4KASghMdph5ECIc+7P9@9e6d0","beachcomber_gray__walk_right_000","d1i4KASghMdph5ECIc+7P9@3f913","beachcomber_gray__walk_right_001","d1i4KASghMdph5ECIc+7P9@fe875","beachcomber_gray__walk_right_002","d1i4KASghMdph5ECIc+7P9@ba548","beachcomber_gray__walk_right_003","d1i4KASghMdph5ECIc+7P9@7639c"]}],[1],0,[],[],[]],[[{"name":"beachcomber_gray__walk_back_000","rect":{"x":64,"y":0,"width":16,"height":32},"offset":{"x":0,"y":0},"originalSize":{"width":16,"height":32},"rotated":false,"capInsets":[0,0,0,0],"vertices":{"rawPosition":[],"indexes":[],"uv":[],"nuv":[],"minPos":{"x":0,"y":0,"z":0},"maxPos":{"x":0,"y":0,"z":0}},"packable":true,"pixelsToUnit":100,"pivot":{"x":0.5,"y":0.5},"meshType":0}],[0],0,[0],[0],[0]],[[{"name":"beachcomber_gray__walk_left_002","rect":{"x":224,"y":0,"width":16,"height":32},"offset":{"x":0,"y":0},"originalSize":{"width":16,"height":32},"rotated":false,"capInsets":[0,0,0,0],"vertices":{"rawPosition":[],"indexes":[],"uv":[],"nuv":[],"minPos":{"x":0,"y":0,"z":0},"maxPos":{"x":0,"y":0,"z":0}},"packable":true,"pixelsToUnit":100,"pivot":{"x":0.5,"y":0.5},"meshType":0}],[0],0,[0],[0],[0]],[[{"name":"beachcomber_gray__face_left","rect":{"x":32,"y":0,"width":16,"height":32},"offset":{"x":0,"y":0},"originalSize":{"width":16,"height":32},"rotated":false,"capInsets":[0,0,0,0],"vertices":{"rawPosition":[],"indexes":[],"uv":[],"nuv":[],"minPos":{"x":0,"y":0,"z":0},"maxPos":{"x":0,"y":0,"z":0}},"packable":true,"pixelsToUnit":100,"pivot":{"x":0.5,"y":0.5},"meshType":0}],[0],0,[0],[0],[0]],[[{"name":"beachcomber_gray__walk_front_001","rect":{"x":144,"y":0,"width":16,"height":32},"offset":{"x":0,"y":0},"originalSize":{"width":16,"height":32},"rotated":false,"capInsets":[0,0,0,0],"vertices":{"rawPosition":[],"indexes":[],"uv":[],"nuv":[],"minPos":{"x":0,"y":0,"z":0},"maxPos":{"x":0,"y":0,"z":0}},"packable":true,"pixelsToUnit":100,"pivot":{"x":0.5,"y":0.5},"meshType":0}],[0],0,[0],[0],[0]],[[{"name":"beachcomber_gray__walk_right_000","rect":{"x":256,"y":0,"width":16,"height":32},"offset":{"x":0,"y":0},"originalSize":{"width":16,"height":32},"rotated":false,"capInsets":[0,0,0,0],"vertices":{"rawPosition":[],"indexes":[],"uv":[],"nuv":[],"minPos":{"x":0,"y":0,"z":0},"maxPos":{"x":0,"y":0,"z":0}},"packable":true,"pixelsToUnit":100,"pivot":{"x":0.5,"y":0.5},"meshType":0}],[0],0,[0],[0],[0]],[[{"name":"beachcomber_gray__walk_back_001","rect":{"x":80,"y":0,"width":16,"height":32},"offset":{"x":0,"y":0},"originalSize":{"width":16,"height":32},"rotated":false,"capInsets":[0,0,0,0],"vertices":{"rawPosition":[],"indexes":[],"uv":[],"nuv":[],"minPos":{"x":0,"y":0,"z":0},"maxPos":{"x":0,"y":0,"z":0}},"packable":true,"pixelsToUnit":100,"pivot":{"x":0.5,"y":0.5},"meshType":0}],[0],0,[0],[0],[0]],[[{"name":"beachcomber_gray__walk_front_000","rect":{"x":128,"y":0,"width":16,"height":32},"offset":{"x":0,"y":0},"originalSize":{"width":16,"height":32},"rotated":false,"capInsets":[0,0,0,0],"vertices":{"rawPosition":[],"indexes":[],"uv":[],"nuv":[],"minPos":{"x":0,"y":0,"z":0},"maxPos":{"x":0,"y":0,"z":0}},"packable":true,"pixelsToUnit":100,"pivot":{"x":0.5,"y":0.5},"meshType":0}],[0],0,[0],[0],[0]],[[{"name":"beachcomber_gray__face_back","rect":{"x":0,"y":0,"width":16,"height":32},"offset":{"x":0,"y":0},"originalSize":{"width":16,"height":32},"rotated":false,"capInsets":[0,0,0,0],"vertices":{"rawPosition":[],"indexes":[],"uv":[],"nuv":[],"minPos":{"x":0,"y":0,"z":0},"maxPos":{"x":0,"y":0,"z":0}},"packable":true,"pixelsToUnit":100,"pivot":{"x":0.5,"y":0.5},"meshType":0}],[0],0,[0],[0],[0]],[[{"name":"beachcomber_gray__walk_front_002","rect":{"x":160,"y":0,"width":16,"height":32},"offset":{"x":0,"y":0},"originalSize":{"width":16,"height":32},"rotated":false,"capInsets":[0,0,0,0],"vertices":{"rawPosition":[],"indexes":[],"uv":[],"nuv":[],"minPos":{"x":0,"y":0,"z":0},"maxPos":{"x":0,"y":0,"z":0}},"packable":true,"pixelsToUnit":100,"pivot":{"x":0.5,"y":0.5},"meshType":0}],[0],0,[0],[0],[0]],[[{"name":"beachcomber_gray__walk_right_003","rect":{"x":304,"y":0,"width":16,"height":32},"offset":{"x":0,"y":0},"originalSize":{"width":16,"height":32},"rotated":false,"capInsets":[0,0,0,0],"vertices":{"rawPosition":[],"indexes":[],"uv":[],"nuv":[],"minPos":{"x":0,"y":0,"z":0},"maxPos":{"x":0,"y":0,"z":0}},"packable":true,"pixelsToUnit":100,"pivot":{"x":0.5,"y":0.5},"meshType":0}],[0],0,[0],[0],[0]],[[{"name":"beachcomber_gray__face_front","rect":{"x":16,"y":0,"width":16,"height":32},"offset":{"x":0,"y":0},"originalSize":{"width":16,"height":32},"rotated":false,"capInsets":[0,0,0,0],"vertices":{"rawPosition":[],"indexes":[],"uv":[],"nuv":[],"minPos":{"x":0,"y":0,"z":0},"maxPos":{"x":0,"y":0,"z":0}},"packable":true,"pixelsToUnit":100,"pivot":{"x":0.5,"y":0.5},"meshType":0}],[0],0,[0],[0],[0]],[[{"name":"beachcomber_gray__walk_back_002","rect":{"x":96,"y":0,"width":16,"height":32},"offset":{"x":0,"y":0},"originalSize":{"width":16,"height":32},"rotated":false,"capInsets":[0,0,0,0],"vertices":{"rawPosition":[],"indexes":[],"uv":[],"nuv":[],"minPos":{"x":0,"y":0,"z":0},"maxPos":{"x":0,"y":0,"z":0}},"packable":true,"pixelsToUnit":100,"pivot":{"x":0.5,"y":0.5},"meshType":0}],[0],0,[0],[0],[0]],[[{"name":"beachcomber_gray__walk_front_003","rect":{"x":176,"y":0,"width":16,"height":32},"offset":{"x":0,"y":0},"originalSize":{"width":16,"height":32},"rotated":false,"capInsets":[0,0,0,0],"vertices":{"rawPosition":[],"indexes":[],"uv":[],"nuv":[],"minPos":{"x":0,"y":0,"z":0},"maxPos":{"x":0,"y":0,"z":0}},"packable":true,"pixelsToUnit":100,"pivot":{"x":0.5,"y":0.5},"meshType":0}],[0],0,[0],[0],[0]],[[{"name":"beachcomber_gray__walk_left_003","rect":{"x":240,"y":0,"width":16,"height":32},"offset":{"x":0,"y":0},"originalSize":{"width":16,"height":32},"rotated":false,"capInsets":[0,0,0,0],"vertices":{"rawPosition":[],"indexes":[],"uv":[],"nuv":[],"minPos":{"x":0,"y":0,"z":0},"maxPos":{"x":0,"y":0,"z":0}},"packable":true,"pixelsToUnit":100,"pivot":{"x":0.5,"y":0.5},"meshType":0}],[0],0,[0],[0],[0]],[[{"name":"beachcomber_gray__walk_left_000","rect":{"x":192,"y":0,"width":16,"height":32},"offset":{"x":0,"y":0},"originalSize":{"width":16,"height":32},"rotated":false,"capInsets":[0,0,0,0],"vertices":{"rawPosition":[],"indexes":[],"uv":[],"nuv":[],"minPos":{"x":0,"y":0,"z":0},"maxPos":{"x":0,"y":0,"z":0}},"packable":true,"pixelsToUnit":100,"pivot":{"x":0.5,"y":0.5},"meshType":0}],[0],0,[0],[0],[0]],[[{"name":"beachcomber_gray__face_right","rect":{"x":48,"y":0,"width":16,"height":32},"offset":{"x":0,"y":0},"originalSize":{"width":16,"height":32},"rotated":false,"capInsets":[0,0,0,0],"vertices":{"rawPosition":[],"indexes":[],"uv":[],"nuv":[],"minPos":{"x":0,"y":0,"z":0},"maxPos":{"x":0,"y":0,"z":0}},"packable":true,"pixelsToUnit":100,"pivot":{"x":0.5,"y":0.5},"meshType":0}],[0],0,[0],[0],[0]],[[{"name":"beachcomber_gray__walk_left_001","rect":{"x":208,"y":0,"width":16,"height":32},"offset":{"x":0,"y":0},"originalSize":{"width":16,"height":32},"rotated":false,"capInsets":[0,0,0,0],"vertices":{"rawPosition":[],"indexes":[],"uv":[],"nuv":[],"minPos":{"x":0,"y":0,"z":0},"maxPos":{"x":0,"y":0,"z":0}},"packable":true,"pixelsToUnit":100,"pivot":{"x":0.5,"y":0.5},"meshType":0}],[0],0,[0],[0],[0]],[[{"name":"beachcomber_gray__walk_right_002","rect":{"x":288,"y":0,"width":16,"height":32},"offset":{"x":0,"y":0},"originalSize":{"width":16,"height":32},"rotated":false,"capInsets":[0,0,0,0],"vertices":{"rawPosition":[],"indexes":[],"uv":[],"nuv":[],"minPos":{"x":0,"y":0,"z":0},"maxPos":{"x":0,"y":0,"z":0}},"packable":true,"pixelsToUnit":100,"pivot":{"x":0.5,"y":0.5},"meshType":0}],[0],0,[0],[0],[0]],[[{"name":"beachcomber_gray__walk_back_003","rect":{"x":112,"y":0,"width":16,"height":32},"offset":{"x":0,"y":0},"originalSize":{"width":16,"height":32},"rotated":false,"capInsets":[0,0,0,0],"vertices":{"rawPosition":[],"indexes":[],"uv":[],"nuv":[],"minPos":{"x":0,"y":0,"z":0},"maxPos":{"x":0,"y":0,"z":0}},"packable":true,"pixelsToUnit":100,"pivot":{"x":0.5,"y":0.5},"meshType":0}],[0],0,[0],[0],[0]],[[{"name":"beachcomber_gray__walk_right_001","rect":{"x":272,"y":0,"width":16,"height":32},"offset":{"x":0,"y":0},"originalSize":{"width":16,"height":32},"rotated":false,"capInsets":[0,0,0,0],"vertices":{"rawPosition":[],"indexes":[],"uv":[],"nuv":[],"minPos":{"x":0,"y":0,"z":0},"maxPos":{"x":0,"y":0,"z":0}},"packable":true,"pixelsToUnit":100,"pivot":{"x":0.5,"y":0.5},"meshType":0}],[0],0,[0],[0],[0]]]]
